trg_etcd3_client/__init__.py
trg_etcd3_client/aio_client.py
trg_etcd3_client/baseclient.py
trg_etcd3_client/client.py
trg_etcd3_client/models.py
trg_etcd3_client/swagger_helper.py
trg_etcd3_client/utils.py
trg_etcd3_client/version.py
trg_etcd3_client/apis/__init__.py
trg_etcd3_client/apis/auth.py
trg_etcd3_client/apis/base.py
trg_etcd3_client/apis/cluster.py
trg_etcd3_client/apis/extra.py
trg_etcd3_client/apis/kv.py
trg_etcd3_client/apis/lease.py
trg_etcd3_client/apis/lock.py
trg_etcd3_client/apis/maintenance.py
trg_etcd3_client/apis/watch.py
trg_etcd3_client/contrib/__init__.py
trg_etcd3_client/errors/__init__.py
trg_etcd3_client/errors/errors.py
trg_etcd3_client/errors/go_etcd_rpctypes_error.py
trg_etcd3_client/errors/go_grpc_codes.py
trg_etcd3_client/errors/go_grpc_gateway_errors.py
trg_etcd3_client/errors/go_net_http_status.py
trg_etcd3_client/stateful/__init__.py
trg_etcd3_client/stateful/lease.py
trg_etcd3_client/stateful/lock.py
trg_etcd3_client/stateful/transaction.py
trg_etcd3_client/stateful/watch.py
trg_etcd3_client/swaggerdefs/__init__.py
trg_etcd3_client/swaggerdefs/v3_2_x/__init__.py
trg_etcd3_client/swaggerdefs/v3_3_x/__init__.py
trg_etcd3_client-0.1.6.dist-info/LICENSE
trg_etcd3_client-0.1.6.dist-info/METADATA
trg_etcd3_client-0.1.6.dist-info/WHEEL
trg_etcd3_client-0.1.6.dist-info/top_level.txt
trg_etcd3_client-0.1.6.dist-info/RECORD
