Metadata-Version: 2.1
Name: trg-etcd3-client
Version: 0.1.6
Summary: etcd client
Home-page: UNKNOWN
License: UNKNOWN
Platform: UNKNOWN
Classifier: Programming Language :: Python :: 3
Classifier: Operating System :: OS Independent
